{
  "schemaVersion": "1.0.0",
  "timezone": "Asia/Tokyo",
  "targetDate": "2026-05-22",
  "generatedAt": "2026-05-22T04:03:59+09:00",
  "runType": "intraday",
  "preserveObservedForecastHours": true,
  "model": {
    "name": "lgbm_quantile_q50_intraday_residual",
    "version": "mvp-1",
    "nWeeks": 12
  },
  "peak": {
    "forecastMw": 32280.0,
    "at": "2026-05-22T09:00:00+09:00",
    "interval": {
      "p95Lower": 30992.1,
      "p95Upper": 34399.1
    }
  },
  "observationSummary": {
    "actualHoursAtGeneration": 3,
    "observedActualHoursAtGeneration": 3,
    "fallbackActualHoursAtGeneration": 0,
    "lastActualHour": 2,
    "lastObservedActualHour": 2,
    "lastFallbackActualHour": null
  },
  "series": [
    {
      "ts": "2026-05-22T00:00:00+09:00",
      "forecastMw": 24007.4,
      "p95LowerMw": 23507.4,
      "p95UpperMw": 25028.7,
      "p99LowerMw": 23007.4,
      "p99UpperMw": 26050.0
    },
    {
      "ts": "2026-05-22T01:00:00+09:00",
      "forecastMw": 22838.2,
      "p95LowerMw": 22234.1,
      "p95UpperMw": 23338.2,
      "p99LowerMw": 21630.0,
      "p99UpperMw": 23838.2
    },
    {
      "ts": "2026-05-22T02:00:00+09:00",
      "forecastMw": 22294.8,
      "p95LowerMw": 21794.8,
      "p95UpperMw": 22877.3,
      "p99LowerMw": 21294.8,
      "p99UpperMw": 23459.8
    },
    {
      "ts": "2026-05-22T03:00:00+09:00",
      "forecastMw": 22130.8,
      "p95LowerMw": 21630.8,
      "p95UpperMw": 22717.2,
      "p99LowerMw": 21130.8,
      "p99UpperMw": 23303.6
    },
    {
      "ts": "2026-05-22T04:00:00+09:00",
      "forecastMw": 22195.9,
      "p95LowerMw": 21695.9,
      "p95UpperMw": 23284.8,
      "p99LowerMw": 21195.9,
      "p99UpperMw": 24373.7
    },
    {
      "ts": "2026-05-22T05:00:00+09:00",
      "forecastMw": 23093.7,
      "p95LowerMw": 22519.3,
      "p95UpperMw": 23694.5,
      "p99LowerMw": 21944.9,
      "p99UpperMw": 24295.3
    },
    {
      "ts": "2026-05-22T06:00:00+09:00",
      "forecastMw": 24275.3,
      "p95LowerMw": 23716.1,
      "p95UpperMw": 25635.8,
      "p99LowerMw": 23156.9,
      "p99UpperMw": 26996.3
    },
    {
      "ts": "2026-05-22T07:00:00+09:00",
      "forecastMw": 26682.8,
      "p95LowerMw": 25820.3,
      "p95UpperMw": 28153.3,
      "p99LowerMw": 24957.8,
      "p99UpperMw": 29623.8
    },
    {
      "ts": "2026-05-22T08:00:00+09:00",
      "forecastMw": 29900.6,
      "p95LowerMw": 28495.7,
      "p95UpperMw": 31325.4,
      "p99LowerMw": 27090.8,
      "p99UpperMw": 32750.2
    },
    {
      "ts": "2026-05-22T09:00:00+09:00",
      "forecastMw": 32280.0,
      "p95LowerMw": 30992.1,
      "p95UpperMw": 34399.1,
      "p99LowerMw": 29704.2,
      "p99UpperMw": 36518.2
    },
    {
      "ts": "2026-05-22T10:00:00+09:00",
      "forecastMw": 32104.4,
      "p95LowerMw": 30636.9,
      "p95UpperMw": 34183.1,
      "p99LowerMw": 29169.4,
      "p99UpperMw": 36261.8
    },
    {
      "ts": "2026-05-22T11:00:00+09:00",
      "forecastMw": 31300.3,
      "p95LowerMw": 30177.2,
      "p95UpperMw": 34129.4,
      "p99LowerMw": 29054.1,
      "p99UpperMw": 36958.5
    },
    {
      "ts": "2026-05-22T12:00:00+09:00",
      "forecastMw": 29095.3,
      "p95LowerMw": 28595.3,
      "p95UpperMw": 31649.5,
      "p99LowerMw": 28095.3,
      "p99UpperMw": 34203.7
    },
    {
      "ts": "2026-05-22T13:00:00+09:00",
      "forecastMw": 29693.3,
      "p95LowerMw": 29193.3,
      "p95UpperMw": 33028.3,
      "p99LowerMw": 28693.3,
      "p99UpperMw": 36363.3
    },
    {
      "ts": "2026-05-22T14:00:00+09:00",
      "forecastMw": 29790.5,
      "p95LowerMw": 29290.5,
      "p95UpperMw": 33079.9,
      "p99LowerMw": 28790.5,
      "p99UpperMw": 36369.3
    },
    {
      "ts": "2026-05-22T15:00:00+09:00",
      "forecastMw": 29989.6,
      "p95LowerMw": 29489.6,
      "p95UpperMw": 32372.4,
      "p99LowerMw": 28989.6,
      "p99UpperMw": 34755.2
    },
    {
      "ts": "2026-05-22T16:00:00+09:00",
      "forecastMw": 30010.5,
      "p95LowerMw": 29510.5,
      "p95UpperMw": 32606.2,
      "p99LowerMw": 29010.5,
      "p99UpperMw": 35201.9
    },
    {
      "ts": "2026-05-22T17:00:00+09:00",
      "forecastMw": 29974.5,
      "p95LowerMw": 29474.5,
      "p95UpperMw": 32017.0,
      "p99LowerMw": 28974.5,
      "p99UpperMw": 34059.5
    },
    {
      "ts": "2026-05-22T18:00:00+09:00",
      "forecastMw": 29787.9,
      "p95LowerMw": 29025.7,
      "p95UpperMw": 31754.0,
      "p99LowerMw": 28263.5,
      "p99UpperMw": 33720.1
    },
    {
      "ts": "2026-05-22T19:00:00+09:00",
      "forecastMw": 29249.5,
      "p95LowerMw": 28569.9,
      "p95UpperMw": 31507.4,
      "p99LowerMw": 27890.3,
      "p99UpperMw": 33765.3
    },
    {
      "ts": "2026-05-22T20:00:00+09:00",
      "forecastMw": 28208.4,
      "p95LowerMw": 27223.0,
      "p95UpperMw": 30018.9,
      "p99LowerMw": 26237.6,
      "p99UpperMw": 31829.4
    },
    {
      "ts": "2026-05-22T21:00:00+09:00",
      "forecastMw": 26663.1,
      "p95LowerMw": 26163.1,
      "p95UpperMw": 28588.2,
      "p99LowerMw": 25663.1,
      "p99UpperMw": 30513.3
    },
    {
      "ts": "2026-05-22T22:00:00+09:00",
      "forecastMw": 25332.0,
      "p95LowerMw": 24832.0,
      "p95UpperMw": 26897.1,
      "p99LowerMw": 24332.0,
      "p99UpperMw": 28462.2
    },
    {
      "ts": "2026-05-22T23:00:00+09:00",
      "forecastMw": 24216.8,
      "p95LowerMw": 23716.8,
      "p95UpperMw": 25473.9,
      "p99LowerMw": 23216.8,
      "p99UpperMw": 26731.0
    }
  ]
}