{
  "date": "2026-05-14",
  "timezone": "Asia/Tokyo",
  "availability": "ok",
  "series": [
    {
      "ts": "2026-05-14T00:00:00+09:00",
      "actualMw": null,
      "actualSource": null,
      "tepcoForecastMw": 22610.0,
      "usagePct": null,
      "supplyMw": 24820.0
    },
    {
      "ts": "2026-05-14T01:00:00+09:00",
      "actualMw": null,
      "actualSource": null,
      "tepcoForecastMw": 21640.0,
      "usagePct": null,
      "supplyMw": 23990.0
    },
    {
      "ts": "2026-05-14T02:00:00+09:00",
      "actualMw": null,
      "actualSource": null,
      "tepcoForecastMw": 21550.0,
      "usagePct": null,
      "supplyMw": 23860.0
    },
    {
      "ts": "2026-05-14T03:00:00+09:00",
      "actualMw": null,
      "actualSource": null,
      "tepcoForecastMw": 21910.0,
      "usagePct": null,
      "supplyMw": 24050.0
    },
    {
      "ts": "2026-05-14T04:00:00+09:00",
      "actualMw": null,
      "actualSource": null,
      "tepcoForecastMw": 22220.0,
      "usagePct": null,
      "supplyMw": 24380.0
    },
    {
      "ts": "2026-05-14T05:00:00+09:00",
      "actualMw": null,
      "actualSource": null,
      "tepcoForecastMw": 21990.0,
      "usagePct": null,
      "supplyMw": 24390.0
    },
    {
      "ts": "2026-05-14T06:00:00+09:00",
      "actualMw": null,
      "actualSource": null,
      "tepcoForecastMw": 22610.0,
      "usagePct": null,
      "supplyMw": 27510.0
    },
    {
      "ts": "2026-05-14T07:00:00+09:00",
      "actualMw": null,
      "actualSource": null,
      "tepcoForecastMw": 24370.0,
      "usagePct": null,
      "supplyMw": 31140.0
    },
    {
      "ts": "2026-05-14T08:00:00+09:00",
      "actualMw": null,
      "actualSource": null,
      "tepcoForecastMw": 28010.0,
      "usagePct": null,
      "supplyMw": 34500.0
    },
    {
      "ts": "2026-05-14T09:00:00+09:00",
      "actualMw": null,
      "actualSource": null,
      "tepcoForecastMw": 30610.0,
      "usagePct": null,
      "supplyMw": 37510.0
    },
    {
      "ts": "2026-05-14T10:00:00+09:00",
      "actualMw": null,
      "actualSource": null,
      "tepcoForecastMw": 31470.0,
      "usagePct": null,
      "supplyMw": 38440.0
    },
    {
      "ts": "2026-05-14T11:00:00+09:00",
      "actualMw": null,
      "actualSource": null,
      "tepcoForecastMw": 32370.0,
      "usagePct": null,
      "supplyMw": 39040.0
    },
    {
      "ts": "2026-05-14T12:00:00+09:00",
      "actualMw": null,
      "actualSource": null,
      "tepcoForecastMw": 31430.0,
      "usagePct": null,
      "supplyMw": 38660.0
    },
    {
      "ts": "2026-05-14T13:00:00+09:00",
      "actualMw": null,
      "actualSource": null,
      "tepcoForecastMw": 31980.0,
      "usagePct": null,
      "supplyMw": 37800.0
    },
    {
      "ts": "2026-05-14T14:00:00+09:00",
      "actualMw": null,
      "actualSource": null,
      "tepcoForecastMw": 31520.0,
      "usagePct": null,
      "supplyMw": 36420.0
    },
    {
      "ts": "2026-05-14T15:00:00+09:00",
      "actualMw": null,
      "actualSource": null,
      "tepcoForecastMw": 31270.0,
      "usagePct": null,
      "supplyMw": 34840.0
    },
    {
      "ts": "2026-05-14T16:00:00+09:00",
      "actualMw": null,
      "actualSource": null,
      "tepcoForecastMw": 31370.0,
      "usagePct": null,
      "supplyMw": 34430.0
    },
    {
      "ts": "2026-05-14T17:00:00+09:00",
      "actualMw": null,
      "actualSource": null,
      "tepcoForecastMw": 30190.0,
      "usagePct": null,
      "supplyMw": 33130.0
    },
    {
      "ts": "2026-05-14T18:00:00+09:00",
      "actualMw": null,
      "actualSource": null,
      "tepcoForecastMw": 30280.0,
      "usagePct": null,
      "supplyMw": 33230.0
    },
    {
      "ts": "2026-05-14T19:00:00+09:00",
      "actualMw": null,
      "actualSource": null,
      "tepcoForecastMw": 29660.0,
      "usagePct": null,
      "supplyMw": 32540.0
    },
    {
      "ts": "2026-05-14T20:00:00+09:00",
      "actualMw": null,
      "actualSource": null,
      "tepcoForecastMw": 28170.0,
      "usagePct": null,
      "supplyMw": 30910.0
    },
    {
      "ts": "2026-05-14T21:00:00+09:00",
      "actualMw": null,
      "actualSource": null,
      "tepcoForecastMw": 26690.0,
      "usagePct": null,
      "supplyMw": 29290.0
    },
    {
      "ts": "2026-05-14T22:00:00+09:00",
      "actualMw": null,
      "actualSource": null,
      "tepcoForecastMw": 25640.0,
      "usagePct": null,
      "supplyMw": 28130.0
    },
    {
      "ts": "2026-05-14T23:00:00+09:00",
      "actualMw": null,
      "actualSource": null,
      "tepcoForecastMw": 24340.0,
      "usagePct": null,
      "supplyMw": 26830.0
    }
  ]
}