{
  "date": "2026-05-28",
  "timezone": "Asia/Tokyo",
  "availability": "ok",
  "model": {
    "name": "lgbm_quantile_q50",
    "version": "mvp-1",
    "nWeeks": 12
  },
  "peak": {
    "forecastMw": 34786.7,
    "at": "2026-05-28T14:00:00+09:00",
    "interval": {
      "p95Lower": 31825.8,
      "p95Upper": 36309.0
    }
  },
  "series": [
    {
      "ts": "2026-05-28T00:00:00+09:00",
      "forecastMw": 24340.0,
      "p95LowerMw": 23260.5,
      "p95UpperMw": 25131.3,
      "p99LowerMw": 22181.0,
      "p99UpperMw": 25922.6
    },
    {
      "ts": "2026-05-28T01:00:00+09:00",
      "forecastMw": 22844.2,
      "p95LowerMw": 22344.2,
      "p95UpperMw": 23859.2,
      "p99LowerMw": 21844.2,
      "p99UpperMw": 24874.2
    },
    {
      "ts": "2026-05-28T02:00:00+09:00",
      "forecastMw": 22665.4,
      "p95LowerMw": 22165.4,
      "p95UpperMw": 23674.3,
      "p99LowerMw": 21665.4,
      "p99UpperMw": 24683.2
    },
    {
      "ts": "2026-05-28T03:00:00+09:00",
      "forecastMw": 22707.2,
      "p95LowerMw": 22207.2,
      "p95UpperMw": 23789.3,
      "p99LowerMw": 21707.2,
      "p99UpperMw": 24871.4
    },
    {
      "ts": "2026-05-28T04:00:00+09:00",
      "forecastMw": 23077.3,
      "p95LowerMw": 22577.3,
      "p95UpperMw": 24041.2,
      "p99LowerMw": 22077.3,
      "p99UpperMw": 25005.1
    },
    {
      "ts": "2026-05-28T05:00:00+09:00",
      "forecastMw": 23100.5,
      "p95LowerMw": 22600.5,
      "p95UpperMw": 24133.4,
      "p99LowerMw": 22100.5,
      "p99UpperMw": 25166.3
    },
    {
      "ts": "2026-05-28T06:00:00+09:00",
      "forecastMw": 24081.8,
      "p95LowerMw": 23334.9,
      "p95UpperMw": 25443.4,
      "p99LowerMw": 22588.0,
      "p99UpperMw": 26805.0
    },
    {
      "ts": "2026-05-28T07:00:00+09:00",
      "forecastMw": 26208.4,
      "p95LowerMw": 25465.3,
      "p95UpperMw": 27622.4,
      "p99LowerMw": 24722.2,
      "p99UpperMw": 29036.4
    },
    {
      "ts": "2026-05-28T08:00:00+09:00",
      "forecastMw": 29815.4,
      "p95LowerMw": 28274.2,
      "p95UpperMw": 31345.0,
      "p99LowerMw": 26733.0,
      "p99UpperMw": 32874.6
    },
    {
      "ts": "2026-05-28T09:00:00+09:00",
      "forecastMw": 33078.4,
      "p95LowerMw": 30829.7,
      "p95UpperMw": 34544.8,
      "p99LowerMw": 28581.0,
      "p99UpperMw": 36011.2
    },
    {
      "ts": "2026-05-28T10:00:00+09:00",
      "forecastMw": 32972.1,
      "p95LowerMw": 30867.9,
      "p95UpperMw": 34465.1,
      "p99LowerMw": 28763.7,
      "p99UpperMw": 35958.1
    },
    {
      "ts": "2026-05-28T11:00:00+09:00",
      "forecastMw": 33626.2,
      "p95LowerMw": 31317.1,
      "p95UpperMw": 35292.1,
      "p99LowerMw": 29008.0,
      "p99UpperMw": 36958.0
    },
    {
      "ts": "2026-05-28T12:00:00+09:00",
      "forecastMw": 32530.9,
      "p95LowerMw": 30410.0,
      "p95UpperMw": 34081.4,
      "p99LowerMw": 28289.1,
      "p99UpperMw": 35631.9
    },
    {
      "ts": "2026-05-28T13:00:00+09:00",
      "forecastMw": 33958.3,
      "p95LowerMw": 31397.7,
      "p95UpperMw": 35752.2,
      "p99LowerMw": 28837.1,
      "p99UpperMw": 37546.1
    },
    {
      "ts": "2026-05-28T14:00:00+09:00",
      "forecastMw": 34786.7,
      "p95LowerMw": 31825.8,
      "p95UpperMw": 36309.0,
      "p99LowerMw": 28864.9,
      "p99UpperMw": 37831.3
    },
    {
      "ts": "2026-05-28T15:00:00+09:00",
      "forecastMw": 33755.4,
      "p95LowerMw": 31427.3,
      "p95UpperMw": 35536.1,
      "p99LowerMw": 29099.2,
      "p99UpperMw": 37316.8
    },
    {
      "ts": "2026-05-28T16:00:00+09:00",
      "forecastMw": 33942.8,
      "p95LowerMw": 31498.1,
      "p95UpperMw": 35790.8,
      "p99LowerMw": 29053.4,
      "p99UpperMw": 37638.8
    },
    {
      "ts": "2026-05-28T17:00:00+09:00",
      "forecastMw": 32865.9,
      "p95LowerMw": 30781.0,
      "p95UpperMw": 34471.2,
      "p99LowerMw": 28696.1,
      "p99UpperMw": 36076.5
    },
    {
      "ts": "2026-05-28T18:00:00+09:00",
      "forecastMw": 32513.2,
      "p95LowerMw": 30643.8,
      "p95UpperMw": 34592.0,
      "p99LowerMw": 28774.4,
      "p99UpperMw": 36670.8
    },
    {
      "ts": "2026-05-28T19:00:00+09:00",
      "forecastMw": 32072.8,
      "p95LowerMw": 30369.7,
      "p95UpperMw": 33363.6,
      "p99LowerMw": 28666.6,
      "p99UpperMw": 34654.4
    },
    {
      "ts": "2026-05-28T20:00:00+09:00",
      "forecastMw": 30273.4,
      "p95LowerMw": 28616.3,
      "p95UpperMw": 31231.7,
      "p99LowerMw": 26959.2,
      "p99UpperMw": 32190.0
    },
    {
      "ts": "2026-05-28T21:00:00+09:00",
      "forecastMw": 28104.8,
      "p95LowerMw": 27295.2,
      "p95UpperMw": 29523.8,
      "p99LowerMw": 26485.8,
      "p99UpperMw": 30942.8
    },
    {
      "ts": "2026-05-28T22:00:00+09:00",
      "forecastMw": 27008.2,
      "p95LowerMw": 26489.3,
      "p95UpperMw": 28489.7,
      "p99LowerMw": 25970.4,
      "p99UpperMw": 29971.2
    },
    {
      "ts": "2026-05-28T23:00:00+09:00",
      "forecastMw": 25727.6,
      "p95LowerMw": 25227.6,
      "p95UpperMw": 27067.2,
      "p99LowerMw": 24727.6,
      "p99UpperMw": 28406.8
    }
  ]
}