{
  "date": "2026-06-21",
  "timezone": "Asia/Tokyo",
  "availability": "ok",
  "model": {
    "name": "lgbm_quantile_q50",
    "version": "mvp-1",
    "nWeeks": 12
  },
  "peak": {
    "forecastMw": 29356.1,
    "at": "2026-06-21T18:00:00+09:00",
    "interval": {
      "p95Lower": 27158.1,
      "p95Upper": 30729.9
    }
  },
  "series": [
    {
      "ts": "2026-06-21T00:00:00+09:00",
      "forecastMw": 23941.5,
      "p95LowerMw": 22010.7,
      "p95UpperMw": 26941.5,
      "p99LowerMw": 20079.9,
      "p99UpperMw": 29941.5
    },
    {
      "ts": "2026-06-21T01:00:00+09:00",
      "forecastMw": 22209.9,
      "p95LowerMw": 20873.8,
      "p95UpperMw": 24347.6,
      "p99LowerMw": 19537.7,
      "p99UpperMw": 26485.3
    },
    {
      "ts": "2026-06-21T02:00:00+09:00",
      "forecastMw": 21532.3,
      "p95LowerMw": 20459.1,
      "p95UpperMw": 23249.3,
      "p99LowerMw": 19385.9,
      "p99UpperMw": 24966.3
    },
    {
      "ts": "2026-06-21T03:00:00+09:00",
      "forecastMw": 21910.7,
      "p95LowerMw": 20741.3,
      "p95UpperMw": 23781.7,
      "p99LowerMw": 19571.9,
      "p99UpperMw": 25652.7
    },
    {
      "ts": "2026-06-21T04:00:00+09:00",
      "forecastMw": 21744.2,
      "p95LowerMw": 20549.9,
      "p95UpperMw": 23655.2,
      "p99LowerMw": 19355.6,
      "p99UpperMw": 25566.2
    },
    {
      "ts": "2026-06-21T05:00:00+09:00",
      "forecastMw": 21453.5,
      "p95LowerMw": 20314.1,
      "p95UpperMw": 23276.5,
      "p99LowerMw": 19174.7,
      "p99UpperMw": 25099.5
    },
    {
      "ts": "2026-06-21T06:00:00+09:00",
      "forecastMw": 21187.4,
      "p95LowerMw": 20046.6,
      "p95UpperMw": 23012.7,
      "p99LowerMw": 18905.8,
      "p99UpperMw": 24838.0
    },
    {
      "ts": "2026-06-21T07:00:00+09:00",
      "forecastMw": 22863.4,
      "p95LowerMw": 21706.1,
      "p95UpperMw": 24715.2,
      "p99LowerMw": 20548.8,
      "p99UpperMw": 26567.0
    },
    {
      "ts": "2026-06-21T08:00:00+09:00",
      "forecastMw": 24455.0,
      "p95LowerMw": 22772.4,
      "p95UpperMw": 27147.2,
      "p99LowerMw": 21089.8,
      "p99UpperMw": 29839.4
    },
    {
      "ts": "2026-06-21T09:00:00+09:00",
      "forecastMw": 25476.1,
      "p95LowerMw": 23690.3,
      "p95UpperMw": 28333.4,
      "p99LowerMw": 21904.5,
      "p99UpperMw": 31190.7
    },
    {
      "ts": "2026-06-21T10:00:00+09:00",
      "forecastMw": 27143.7,
      "p95LowerMw": 24143.7,
      "p95UpperMw": 29239.4,
      "p99LowerMw": 21143.7,
      "p99UpperMw": 31335.1
    },
    {
      "ts": "2026-06-21T11:00:00+09:00",
      "forecastMw": 27158.3,
      "p95LowerMw": 24295.9,
      "p95UpperMw": 29273.4,
      "p99LowerMw": 21433.5,
      "p99UpperMw": 31388.5
    },
    {
      "ts": "2026-06-21T12:00:00+09:00",
      "forecastMw": 27327.0,
      "p95LowerMw": 24331.8,
      "p95UpperMw": 29837.1,
      "p99LowerMw": 21336.6,
      "p99UpperMw": 32347.2
    },
    {
      "ts": "2026-06-21T13:00:00+09:00",
      "forecastMw": 27096.2,
      "p95LowerMw": 24096.2,
      "p95UpperMw": 30096.2,
      "p99LowerMw": 21096.2,
      "p99UpperMw": 33096.2
    },
    {
      "ts": "2026-06-21T14:00:00+09:00",
      "forecastMw": 27857.8,
      "p95LowerMw": 24857.8,
      "p95UpperMw": 29908.6,
      "p99LowerMw": 21857.8,
      "p99UpperMw": 31959.4
    },
    {
      "ts": "2026-06-21T15:00:00+09:00",
      "forecastMw": 27733.3,
      "p95LowerMw": 24733.3,
      "p95UpperMw": 30237.1,
      "p99LowerMw": 21733.3,
      "p99UpperMw": 32740.9
    },
    {
      "ts": "2026-06-21T16:00:00+09:00",
      "forecastMw": 28321.0,
      "p95LowerMw": 25321.0,
      "p95UpperMw": 30618.9,
      "p99LowerMw": 22321.0,
      "p99UpperMw": 32916.8
    },
    {
      "ts": "2026-06-21T17:00:00+09:00",
      "forecastMw": 28375.4,
      "p95LowerMw": 25586.9,
      "p95UpperMw": 30118.2,
      "p99LowerMw": 22798.4,
      "p99UpperMw": 31861.0
    },
    {
      "ts": "2026-06-21T18:00:00+09:00",
      "forecastMw": 29356.1,
      "p95LowerMw": 27158.1,
      "p95UpperMw": 30729.9,
      "p99LowerMw": 24960.1,
      "p99UpperMw": 32103.7
    },
    {
      "ts": "2026-06-21T19:00:00+09:00",
      "forecastMw": 28903.2,
      "p95LowerMw": 26414.6,
      "p95UpperMw": 30458.5,
      "p99LowerMw": 23926.0,
      "p99UpperMw": 32013.8
    },
    {
      "ts": "2026-06-21T20:00:00+09:00",
      "forecastMw": 27956.0,
      "p95LowerMw": 26097.6,
      "p95UpperMw": 29117.5,
      "p99LowerMw": 24239.2,
      "p99UpperMw": 30279.0
    },
    {
      "ts": "2026-06-21T21:00:00+09:00",
      "forecastMw": 26970.9,
      "p95LowerMw": 24140.7,
      "p95UpperMw": 28739.8,
      "p99LowerMw": 21310.5,
      "p99UpperMw": 30508.7
    },
    {
      "ts": "2026-06-21T22:00:00+09:00",
      "forecastMw": 25556.5,
      "p95LowerMw": 23720.0,
      "p95UpperMw": 28495.0,
      "p99LowerMw": 21883.5,
      "p99UpperMw": 31433.5
    },
    {
      "ts": "2026-06-21T23:00:00+09:00",
      "forecastMw": 24470.5,
      "p95LowerMw": 23033.9,
      "p95UpperMw": 26769.1,
      "p99LowerMw": 21597.3,
      "p99UpperMw": 29067.7
    }
  ]
}