{
  "date": "2023-08-14",
  "timezone": "Asia/Tokyo",
  "availability": "ok",
  "summary": {
    "critical": 0,
    "warning": 7,
    "info": 0
  },
  "events": [
    {
      "id": "2023-08-14T03:00:00+09:00_reserve_risk",
      "type": "reserve_risk",
      "severity": "warning",
      "startAt": "2023-08-14T03:00:00+09:00",
      "endAt": "2023-08-14T04:00:00+09:00",
      "metric": "usage_pct",
      "usagePct": 90.0,
      "thresholdPct": 90.0,
      "supplyMw": 26570.0,
      "reason": "Usage 90.0% exceeded warning threshold 90.0%",
      "tags": [
        "kpi"
      ]
    },
    {
      "id": "2023-08-14T04:00:00+09:00_reserve_risk",
      "type": "reserve_risk",
      "severity": "warning",
      "startAt": "2023-08-14T04:00:00+09:00",
      "endAt": "2023-08-14T05:00:00+09:00",
      "metric": "usage_pct",
      "usagePct": 91.0,
      "thresholdPct": 90.0,
      "supplyMw": 26410.0,
      "reason": "Usage 91.0% exceeded warning threshold 90.0%",
      "tags": [
        "kpi"
      ]
    },
    {
      "id": "2023-08-14T07:00:00+09:00_reserve_risk",
      "type": "reserve_risk",
      "severity": "warning",
      "startAt": "2023-08-14T07:00:00+09:00",
      "endAt": "2023-08-14T08:00:00+09:00",
      "metric": "usage_pct",
      "usagePct": 91.0,
      "thresholdPct": 90.0,
      "supplyMw": 32870.0,
      "reason": "Usage 91.0% exceeded warning threshold 90.0%",
      "tags": [
        "kpi"
      ]
    },
    {
      "id": "2023-08-14T08:00:00+09:00_reserve_risk",
      "type": "reserve_risk",
      "severity": "warning",
      "startAt": "2023-08-14T08:00:00+09:00",
      "endAt": "2023-08-14T09:00:00+09:00",
      "metric": "usage_pct",
      "usagePct": 91.0,
      "thresholdPct": 90.0,
      "supplyMw": 37700.0,
      "reason": "Usage 91.0% exceeded warning threshold 90.0%",
      "tags": [
        "kpi"
      ]
    },
    {
      "id": "2023-08-14T09:00:00+09:00_reserve_risk",
      "type": "reserve_risk",
      "severity": "warning",
      "startAt": "2023-08-14T09:00:00+09:00",
      "endAt": "2023-08-14T10:00:00+09:00",
      "metric": "usage_pct",
      "usagePct": 90.0,
      "thresholdPct": 90.0,
      "supplyMw": 41380.0,
      "reason": "Usage 90.0% exceeded warning threshold 90.0%",
      "tags": [
        "kpi"
      ]
    },
    {
      "id": "2023-08-14T00:00:00+09:00_drift",
      "type": "drift",
      "severity": "warning",
      "startAt": "2023-08-14T00:00:00+09:00",
      "endAt": "2023-08-14T06:00:00+09:00",
      "metric": "residual_mw",
      "residualAvgMw": 1054.2,
      "method": "ewma",
      "thresholdMw": 800.0,
      "reason": "EWMA residual above ±800 MW for 7 consecutive hours",
      "tags": [
        "residual"
      ]
    },
    {
      "id": "2023-08-14T10:00:00+09:00_drift",
      "type": "drift",
      "severity": "warning",
      "startAt": "2023-08-14T10:00:00+09:00",
      "endAt": "2023-08-14T19:00:00+09:00",
      "metric": "residual_mw",
      "residualAvgMw": -2121.6,
      "method": "ewma",
      "thresholdMw": 800.0,
      "reason": "EWMA residual below ±800 MW for 10 consecutive hours",
      "tags": [
        "residual"
      ]
    }
  ]
}