{
  "date": "2023-02-08",
  "timezone": "Asia/Tokyo",
  "availability": "ok",
  "model": {
    "name": "baseline_dow_hour_mean",
    "version": "mvp-1",
    "nWeeks": 12
  },
  "peak": {
    "forecastMw": 44150.0,
    "at": "2023-02-08T09:00:00+09:00",
    "interval": {
      "p95Lower": 32601.2,
      "p95Upper": 55698.8
    }
  },
  "series": [
    {
      "ts": "2023-02-08T00:00:00+09:00",
      "forecastMw": 32226.0,
      "p95LowerMw": 25684.5,
      "p95UpperMw": 38767.5,
      "p99LowerMw": 23628.6,
      "p99UpperMw": 40823.4
    },
    {
      "ts": "2023-02-08T01:00:00+09:00",
      "forecastMw": 30862.0,
      "p95LowerMw": 24647.7,
      "p95UpperMw": 37076.3,
      "p99LowerMw": 22694.6,
      "p99UpperMw": 39029.4
    },
    {
      "ts": "2023-02-08T02:00:00+09:00",
      "forecastMw": 30302.0,
      "p95LowerMw": 24385.0,
      "p95UpperMw": 36219.0,
      "p99LowerMw": 22525.3,
      "p99UpperMw": 38078.7
    },
    {
      "ts": "2023-02-08T03:00:00+09:00",
      "forecastMw": 30036.0,
      "p95LowerMw": 24298.1,
      "p95UpperMw": 35773.9,
      "p99LowerMw": 22494.7,
      "p99UpperMw": 37577.3
    },
    {
      "ts": "2023-02-08T04:00:00+09:00",
      "forecastMw": 30448.0,
      "p95LowerMw": 24481.1,
      "p95UpperMw": 36414.9,
      "p99LowerMw": 22605.8,
      "p99UpperMw": 38290.2
    },
    {
      "ts": "2023-02-08T05:00:00+09:00",
      "forecastMw": 32496.0,
      "p95LowerMw": 25681.5,
      "p95UpperMw": 39310.5,
      "p99LowerMw": 23539.8,
      "p99UpperMw": 41452.2
    },
    {
      "ts": "2023-02-08T06:00:00+09:00",
      "forecastMw": 37036.0,
      "p95LowerMw": 28576.9,
      "p95UpperMw": 45495.1,
      "p99LowerMw": 25918.3,
      "p99UpperMw": 48153.7
    },
    {
      "ts": "2023-02-08T07:00:00+09:00",
      "forecastMw": 40946.0,
      "p95LowerMw": 31730.6,
      "p95UpperMw": 50161.4,
      "p99LowerMw": 28834.4,
      "p99UpperMw": 53057.6
    },
    {
      "ts": "2023-02-08T08:00:00+09:00",
      "forecastMw": 43676.0,
      "p95LowerMw": 33477.7,
      "p95UpperMw": 53874.3,
      "p99LowerMw": 30272.5,
      "p99UpperMw": 57079.5
    },
    {
      "ts": "2023-02-08T09:00:00+09:00",
      "forecastMw": 44150.0,
      "p95LowerMw": 32601.2,
      "p95UpperMw": 55698.8,
      "p99LowerMw": 28971.6,
      "p99UpperMw": 59328.4
    },
    {
      "ts": "2023-02-08T10:00:00+09:00",
      "forecastMw": 42782.0,
      "p95LowerMw": 30864.0,
      "p95UpperMw": 54700.0,
      "p99LowerMw": 27118.3,
      "p99UpperMw": 58445.7
    },
    {
      "ts": "2023-02-08T11:00:00+09:00",
      "forecastMw": 41474.0,
      "p95LowerMw": 29513.9,
      "p95UpperMw": 53434.1,
      "p99LowerMw": 25755.1,
      "p99UpperMw": 57192.9
    },
    {
      "ts": "2023-02-08T12:00:00+09:00",
      "forecastMw": 39648.0,
      "p95LowerMw": 28753.0,
      "p95UpperMw": 50543.0,
      "p99LowerMw": 25328.9,
      "p99UpperMw": 53967.1
    },
    {
      "ts": "2023-02-08T13:00:00+09:00",
      "forecastMw": 39744.0,
      "p95LowerMw": 28662.8,
      "p95UpperMw": 50825.2,
      "p99LowerMw": 25180.1,
      "p99UpperMw": 54307.9
    },
    {
      "ts": "2023-02-08T14:00:00+09:00",
      "forecastMw": 39038.0,
      "p95LowerMw": 28426.9,
      "p95UpperMw": 49649.1,
      "p99LowerMw": 25092.0,
      "p99UpperMw": 52984.0
    },
    {
      "ts": "2023-02-08T15:00:00+09:00",
      "forecastMw": 39094.0,
      "p95LowerMw": 29208.6,
      "p95UpperMw": 48979.4,
      "p99LowerMw": 26101.7,
      "p99UpperMw": 52086.3
    },
    {
      "ts": "2023-02-08T16:00:00+09:00",
      "forecastMw": 40760.0,
      "p95LowerMw": 30761.0,
      "p95UpperMw": 50759.0,
      "p99LowerMw": 27618.4,
      "p99UpperMw": 53901.6
    },
    {
      "ts": "2023-02-08T17:00:00+09:00",
      "forecastMw": 42782.0,
      "p95LowerMw": 32827.2,
      "p95UpperMw": 52736.8,
      "p99LowerMw": 29698.6,
      "p99UpperMw": 55865.4
    },
    {
      "ts": "2023-02-08T18:00:00+09:00",
      "forecastMw": 43094.0,
      "p95LowerMw": 33288.9,
      "p95UpperMw": 52899.1,
      "p99LowerMw": 30207.3,
      "p99UpperMw": 55980.7
    },
    {
      "ts": "2023-02-08T19:00:00+09:00",
      "forecastMw": 42398.0,
      "p95LowerMw": 32935.6,
      "p95UpperMw": 51860.4,
      "p99LowerMw": 29961.6,
      "p99UpperMw": 54834.4
    },
    {
      "ts": "2023-02-08T20:00:00+09:00",
      "forecastMw": 41376.0,
      "p95LowerMw": 32319.4,
      "p95UpperMw": 50432.6,
      "p99LowerMw": 29473.0,
      "p99UpperMw": 53279.0
    },
    {
      "ts": "2023-02-08T21:00:00+09:00",
      "forecastMw": 39460.0,
      "p95LowerMw": 30881.1,
      "p95UpperMw": 48038.9,
      "p99LowerMw": 28184.8,
      "p99UpperMw": 50735.2
    },
    {
      "ts": "2023-02-08T22:00:00+09:00",
      "forecastMw": 37058.0,
      "p95LowerMw": 29137.2,
      "p95UpperMw": 44978.8,
      "p99LowerMw": 26647.8,
      "p99UpperMw": 47468.2
    },
    {
      "ts": "2023-02-08T23:00:00+09:00",
      "forecastMw": 34490.0,
      "p95LowerMw": 27213.0,
      "p95UpperMw": 41767.0,
      "p99LowerMw": 24925.9,
      "p99UpperMw": 44054.1
    }
  ]
}