{
  "date": "2024-07-01",
  "timezone": "Asia/Tokyo",
  "availability": "ok",
  "model": {
    "name": "baseline_dow_hour_mean",
    "version": "mvp-1",
    "nWeeks": 12
  },
  "peak": {
    "forecastMw": 37780.0,
    "at": "2024-07-01T14:00:00+09:00",
    "interval": {
      "p95Lower": 24013.2,
      "p95Upper": 51546.8
    }
  },
  "series": [
    {
      "ts": "2024-07-01T00:00:00+09:00",
      "forecastMw": 23105.3,
      "p95LowerMw": 19534.6,
      "p95UpperMw": 26676.0,
      "p99LowerMw": 18412.4,
      "p99UpperMw": 27798.2
    },
    {
      "ts": "2024-07-01T01:00:00+09:00",
      "forecastMw": 21954.7,
      "p95LowerMw": 19010.3,
      "p95UpperMw": 24899.1,
      "p99LowerMw": 18084.9,
      "p99UpperMw": 25824.5
    },
    {
      "ts": "2024-07-01T02:00:00+09:00",
      "forecastMw": 21704.7,
      "p95LowerMw": 19234.6,
      "p95UpperMw": 24174.8,
      "p99LowerMw": 18458.3,
      "p99UpperMw": 24951.1
    },
    {
      "ts": "2024-07-01T03:00:00+09:00",
      "forecastMw": 22042.9,
      "p95LowerMw": 19945.9,
      "p95UpperMw": 24140.0,
      "p99LowerMw": 19286.8,
      "p99UpperMw": 24799.1
    },
    {
      "ts": "2024-07-01T04:00:00+09:00",
      "forecastMw": 22351.2,
      "p95LowerMw": 20392.7,
      "p95UpperMw": 24309.7,
      "p99LowerMw": 19777.1,
      "p99UpperMw": 24925.2
    },
    {
      "ts": "2024-07-01T05:00:00+09:00",
      "forecastMw": 22757.1,
      "p95LowerMw": 20541.1,
      "p95UpperMw": 24973.0,
      "p99LowerMw": 19844.7,
      "p99UpperMw": 25669.4
    },
    {
      "ts": "2024-07-01T06:00:00+09:00",
      "forecastMw": 24394.7,
      "p95LowerMw": 21098.2,
      "p95UpperMw": 27691.2,
      "p99LowerMw": 20062.1,
      "p99UpperMw": 28727.3
    },
    {
      "ts": "2024-07-01T07:00:00+09:00",
      "forecastMw": 27496.5,
      "p95LowerMw": 22199.9,
      "p95UpperMw": 32793.0,
      "p99LowerMw": 20535.3,
      "p99UpperMw": 34457.7
    },
    {
      "ts": "2024-07-01T08:00:00+09:00",
      "forecastMw": 31707.6,
      "p95LowerMw": 23825.7,
      "p95UpperMw": 39589.6,
      "p99LowerMw": 21348.5,
      "p99UpperMw": 42066.8
    },
    {
      "ts": "2024-07-01T09:00:00+09:00",
      "forecastMw": 35071.2,
      "p95LowerMw": 24844.3,
      "p95UpperMw": 45298.1,
      "p99LowerMw": 21630.1,
      "p99UpperMw": 48512.2
    },
    {
      "ts": "2024-07-01T10:00:00+09:00",
      "forecastMw": 36361.2,
      "p95LowerMw": 24589.8,
      "p95UpperMw": 48132.5,
      "p99LowerMw": 20890.2,
      "p99UpperMw": 51832.1
    },
    {
      "ts": "2024-07-01T11:00:00+09:00",
      "forecastMw": 37022.4,
      "p95LowerMw": 24403.2,
      "p95UpperMw": 49641.5,
      "p99LowerMw": 20437.2,
      "p99UpperMw": 53607.5
    },
    {
      "ts": "2024-07-01T12:00:00+09:00",
      "forecastMw": 36294.7,
      "p95LowerMw": 22859.1,
      "p95UpperMw": 49730.3,
      "p99LowerMw": 18636.5,
      "p99UpperMw": 53952.9
    },
    {
      "ts": "2024-07-01T13:00:00+09:00",
      "forecastMw": 37578.2,
      "p95LowerMw": 23749.3,
      "p95UpperMw": 51407.2,
      "p99LowerMw": 19403.0,
      "p99UpperMw": 55753.4
    },
    {
      "ts": "2024-07-01T14:00:00+09:00",
      "forecastMw": 37780.0,
      "p95LowerMw": 24013.2,
      "p95UpperMw": 51546.8,
      "p99LowerMw": 19686.5,
      "p99UpperMw": 55873.5
    },
    {
      "ts": "2024-07-01T15:00:00+09:00",
      "forecastMw": 37236.5,
      "p95LowerMw": 23763.4,
      "p95UpperMw": 50709.5,
      "p99LowerMw": 19529.0,
      "p99UpperMw": 54943.9
    },
    {
      "ts": "2024-07-01T16:00:00+09:00",
      "forecastMw": 36722.9,
      "p95LowerMw": 24044.5,
      "p95UpperMw": 49401.3,
      "p99LowerMw": 20059.9,
      "p99UpperMw": 53386.0
    },
    {
      "ts": "2024-07-01T17:00:00+09:00",
      "forecastMw": 35470.0,
      "p95LowerMw": 24252.8,
      "p95UpperMw": 46687.2,
      "p99LowerMw": 20727.4,
      "p99UpperMw": 50212.6
    },
    {
      "ts": "2024-07-01T18:00:00+09:00",
      "forecastMw": 34938.8,
      "p95LowerMw": 25270.7,
      "p95UpperMw": 44606.9,
      "p99LowerMw": 22232.2,
      "p99UpperMw": 47645.5
    },
    {
      "ts": "2024-07-01T19:00:00+09:00",
      "forecastMw": 34029.4,
      "p95LowerMw": 25102.7,
      "p95UpperMw": 42956.1,
      "p99LowerMw": 22297.2,
      "p99UpperMw": 45761.7
    },
    {
      "ts": "2024-07-01T20:00:00+09:00",
      "forecastMw": 32380.0,
      "p95LowerMw": 24346.7,
      "p95UpperMw": 40413.3,
      "p99LowerMw": 21822.0,
      "p99UpperMw": 42938.0
    },
    {
      "ts": "2024-07-01T21:00:00+09:00",
      "forecastMw": 30532.4,
      "p95LowerMw": 23421.9,
      "p95UpperMw": 37642.8,
      "p99LowerMw": 21187.1,
      "p99UpperMw": 39877.6
    },
    {
      "ts": "2024-07-01T22:00:00+09:00",
      "forecastMw": 29050.0,
      "p95LowerMw": 22761.2,
      "p95UpperMw": 35338.8,
      "p99LowerMw": 20784.7,
      "p99UpperMw": 37315.3
    },
    {
      "ts": "2024-07-01T23:00:00+09:00",
      "forecastMw": 27354.1,
      "p95LowerMw": 21905.1,
      "p95UpperMw": 32803.1,
      "p99LowerMw": 20192.6,
      "p99UpperMw": 34515.7
    }
  ]
}