{
  "date": "2025-08-18",
  "timezone": "Asia/Tokyo",
  "availability": "ok",
  "model": {
    "name": "baseline_dow_hour_mean",
    "version": "mvp-1",
    "nWeeks": 12
  },
  "peak": {
    "forecastMw": 47530.4,
    "at": "2025-08-18T13:00:00+09:00",
    "interval": {
      "p95Lower": 32731.5,
      "p95Upper": 62329.3
    }
  },
  "series": [
    {
      "ts": "2025-08-18T00:00:00+09:00",
      "forecastMw": 27690.8,
      "p95LowerMw": 22164.6,
      "p95UpperMw": 33217.0,
      "p99LowerMw": 20427.8,
      "p99UpperMw": 34953.8
    },
    {
      "ts": "2025-08-18T01:00:00+09:00",
      "forecastMw": 25964.4,
      "p95LowerMw": 21050.0,
      "p95UpperMw": 30878.8,
      "p99LowerMw": 19505.4,
      "p99UpperMw": 32423.4
    },
    {
      "ts": "2025-08-18T02:00:00+09:00",
      "forecastMw": 25180.4,
      "p95LowerMw": 20827.9,
      "p95UpperMw": 29532.9,
      "p99LowerMw": 19460.0,
      "p99UpperMw": 30900.8
    },
    {
      "ts": "2025-08-18T03:00:00+09:00",
      "forecastMw": 25074.4,
      "p95LowerMw": 21180.9,
      "p95UpperMw": 28967.9,
      "p99LowerMw": 19957.2,
      "p99UpperMw": 30191.6
    },
    {
      "ts": "2025-08-18T04:00:00+09:00",
      "forecastMw": 25249.2,
      "p95LowerMw": 21423.9,
      "p95UpperMw": 29074.5,
      "p99LowerMw": 20221.7,
      "p99UpperMw": 30276.7
    },
    {
      "ts": "2025-08-18T05:00:00+09:00",
      "forecastMw": 25890.0,
      "p95LowerMw": 21412.7,
      "p95UpperMw": 30367.3,
      "p99LowerMw": 20005.5,
      "p99UpperMw": 31774.5
    },
    {
      "ts": "2025-08-18T06:00:00+09:00",
      "forecastMw": 28356.8,
      "p95LowerMw": 22458.7,
      "p95UpperMw": 34254.9,
      "p99LowerMw": 20605.0,
      "p99UpperMw": 36108.6
    },
    {
      "ts": "2025-08-18T07:00:00+09:00",
      "forecastMw": 33112.0,
      "p95LowerMw": 24901.7,
      "p95UpperMw": 41322.3,
      "p99LowerMw": 22321.3,
      "p99UpperMw": 43902.7
    },
    {
      "ts": "2025-08-18T08:00:00+09:00",
      "forecastMw": 39297.2,
      "p95LowerMw": 28494.4,
      "p95UpperMw": 50100.0,
      "p99LowerMw": 25099.2,
      "p99UpperMw": 53495.2
    },
    {
      "ts": "2025-08-18T09:00:00+09:00",
      "forecastMw": 43905.6,
      "p95LowerMw": 31267.6,
      "p95UpperMw": 56543.6,
      "p99LowerMw": 27295.7,
      "p99UpperMw": 60515.5
    },
    {
      "ts": "2025-08-18T10:00:00+09:00",
      "forecastMw": 45736.8,
      "p95LowerMw": 31990.4,
      "p95UpperMw": 59483.2,
      "p99LowerMw": 27670.2,
      "p99UpperMw": 63803.4
    },
    {
      "ts": "2025-08-18T11:00:00+09:00",
      "forecastMw": 46816.4,
      "p95LowerMw": 32641.6,
      "p95UpperMw": 60991.2,
      "p99LowerMw": 28186.7,
      "p99UpperMw": 65446.1
    },
    {
      "ts": "2025-08-18T12:00:00+09:00",
      "forecastMw": 46374.0,
      "p95LowerMw": 31665.8,
      "p95UpperMw": 61082.2,
      "p99LowerMw": 27043.2,
      "p99UpperMw": 65704.8
    },
    {
      "ts": "2025-08-18T13:00:00+09:00",
      "forecastMw": 47530.4,
      "p95LowerMw": 32731.5,
      "p95UpperMw": 62329.3,
      "p99LowerMw": 28080.4,
      "p99UpperMw": 66980.4
    },
    {
      "ts": "2025-08-18T14:00:00+09:00",
      "forecastMw": 47514.8,
      "p95LowerMw": 32774.6,
      "p95UpperMw": 62255.0,
      "p99LowerMw": 28142.0,
      "p99UpperMw": 66887.6
    },
    {
      "ts": "2025-08-18T15:00:00+09:00",
      "forecastMw": 46965.6,
      "p95LowerMw": 32719.9,
      "p95UpperMw": 61211.3,
      "p99LowerMw": 28242.7,
      "p99UpperMw": 65688.5
    },
    {
      "ts": "2025-08-18T16:00:00+09:00",
      "forecastMw": 46322.0,
      "p95LowerMw": 33105.1,
      "p95UpperMw": 59538.9,
      "p99LowerMw": 28951.2,
      "p99UpperMw": 63692.8
    },
    {
      "ts": "2025-08-18T17:00:00+09:00",
      "forecastMw": 44324.0,
      "p95LowerMw": 32576.4,
      "p95UpperMw": 56071.6,
      "p99LowerMw": 28884.2,
      "p99UpperMw": 59763.8
    },
    {
      "ts": "2025-08-18T18:00:00+09:00",
      "forecastMw": 43034.4,
      "p95LowerMw": 32438.8,
      "p95UpperMw": 53630.0,
      "p99LowerMw": 29108.8,
      "p99UpperMw": 56960.0
    },
    {
      "ts": "2025-08-18T19:00:00+09:00",
      "forecastMw": 41444.0,
      "p95LowerMw": 31656.8,
      "p95UpperMw": 51231.2,
      "p99LowerMw": 28580.8,
      "p99UpperMw": 54307.2
    },
    {
      "ts": "2025-08-18T20:00:00+09:00",
      "forecastMw": 39190.4,
      "p95LowerMw": 30193.0,
      "p95UpperMw": 48187.8,
      "p99LowerMw": 27365.3,
      "p99UpperMw": 51015.5
    },
    {
      "ts": "2025-08-18T21:00:00+09:00",
      "forecastMw": 36803.6,
      "p95LowerMw": 28642.2,
      "p95UpperMw": 44965.0,
      "p99LowerMw": 26077.2,
      "p99UpperMw": 47530.0
    },
    {
      "ts": "2025-08-18T22:00:00+09:00",
      "forecastMw": 34777.2,
      "p95LowerMw": 27337.4,
      "p95UpperMw": 42217.0,
      "p99LowerMw": 24999.2,
      "p99UpperMw": 44555.2
    },
    {
      "ts": "2025-08-18T23:00:00+09:00",
      "forecastMw": 32509.2,
      "p95LowerMw": 25898.6,
      "p95UpperMw": 39119.8,
      "p99LowerMw": 23821.0,
      "p99UpperMw": 41197.4
    }
  ]
}