{
  "date": "2025-10-28",
  "timezone": "Asia/Tokyo",
  "availability": "ok",
  "model": {
    "name": "baseline_dow_hour_mean",
    "version": "mvp-1",
    "nWeeks": 12
  },
  "peak": {
    "forecastMw": 38126.3,
    "at": "2025-10-28T14:00:00+09:00",
    "interval": {
      "p95Lower": 21174.6,
      "p95Upper": 55078.0
    }
  },
  "series": [
    {
      "ts": "2025-10-28T00:00:00+09:00",
      "forecastMw": 25733.3,
      "p95LowerMw": 18752.5,
      "p95UpperMw": 32714.2,
      "p99LowerMw": 16558.5,
      "p99UpperMw": 34908.2
    },
    {
      "ts": "2025-10-28T01:00:00+09:00",
      "forecastMw": 24372.6,
      "p95LowerMw": 18224.5,
      "p95UpperMw": 30520.7,
      "p99LowerMw": 16292.2,
      "p99UpperMw": 32453.0
    },
    {
      "ts": "2025-10-28T02:00:00+09:00",
      "forecastMw": 23956.3,
      "p95LowerMw": 18486.9,
      "p95UpperMw": 29425.7,
      "p99LowerMw": 16767.9,
      "p99UpperMw": 31144.7
    },
    {
      "ts": "2025-10-28T03:00:00+09:00",
      "forecastMw": 24152.6,
      "p95LowerMw": 19272.7,
      "p95UpperMw": 29032.5,
      "p99LowerMw": 17739.1,
      "p99UpperMw": 30566.1
    },
    {
      "ts": "2025-10-28T04:00:00+09:00",
      "forecastMw": 24498.5,
      "p95LowerMw": 19891.9,
      "p95UpperMw": 29105.1,
      "p99LowerMw": 18444.1,
      "p99UpperMw": 30552.9
    },
    {
      "ts": "2025-10-28T05:00:00+09:00",
      "forecastMw": 25274.1,
      "p95LowerMw": 20469.4,
      "p95UpperMw": 30078.8,
      "p99LowerMw": 18959.3,
      "p99UpperMw": 31588.8
    },
    {
      "ts": "2025-10-28T06:00:00+09:00",
      "forecastMw": 26938.9,
      "p95LowerMw": 20817.4,
      "p95UpperMw": 33060.4,
      "p99LowerMw": 18893.5,
      "p99UpperMw": 34984.3
    },
    {
      "ts": "2025-10-28T07:00:00+09:00",
      "forecastMw": 29613.7,
      "p95LowerMw": 21206.4,
      "p95UpperMw": 38021.0,
      "p99LowerMw": 18564.1,
      "p99UpperMw": 40663.4
    },
    {
      "ts": "2025-10-28T08:00:00+09:00",
      "forecastMw": 33334.1,
      "p95LowerMw": 22215.1,
      "p95UpperMw": 44453.0,
      "p99LowerMw": 18720.6,
      "p99UpperMw": 47947.6
    },
    {
      "ts": "2025-10-28T09:00:00+09:00",
      "forecastMw": 36158.9,
      "p95LowerMw": 22933.9,
      "p95UpperMw": 49383.8,
      "p99LowerMw": 18777.5,
      "p99UpperMw": 53540.2
    },
    {
      "ts": "2025-10-28T10:00:00+09:00",
      "forecastMw": 37231.9,
      "p95LowerMw": 22624.6,
      "p95UpperMw": 51839.2,
      "p99LowerMw": 18033.7,
      "p99UpperMw": 56430.0
    },
    {
      "ts": "2025-10-28T11:00:00+09:00",
      "forecastMw": 37808.5,
      "p95LowerMw": 22286.7,
      "p95UpperMw": 53330.3,
      "p99LowerMw": 17408.5,
      "p99UpperMw": 58208.6
    },
    {
      "ts": "2025-10-28T12:00:00+09:00",
      "forecastMw": 36921.1,
      "p95LowerMw": 20505.1,
      "p95UpperMw": 53337.1,
      "p99LowerMw": 15345.8,
      "p99UpperMw": 58496.4
    },
    {
      "ts": "2025-10-28T13:00:00+09:00",
      "forecastMw": 38027.0,
      "p95LowerMw": 21254.9,
      "p95UpperMw": 54799.2,
      "p99LowerMw": 15983.7,
      "p99UpperMw": 60070.4
    },
    {
      "ts": "2025-10-28T14:00:00+09:00",
      "forecastMw": 38126.3,
      "p95LowerMw": 21174.6,
      "p95UpperMw": 55078.0,
      "p99LowerMw": 15846.9,
      "p99UpperMw": 60405.7
    },
    {
      "ts": "2025-10-28T15:00:00+09:00",
      "forecastMw": 37938.9,
      "p95LowerMw": 21066.7,
      "p95UpperMw": 54811.1,
      "p99LowerMw": 15764.0,
      "p99UpperMw": 60113.7
    },
    {
      "ts": "2025-10-28T16:00:00+09:00",
      "forecastMw": 37911.1,
      "p95LowerMw": 21956.5,
      "p95UpperMw": 53865.7,
      "p99LowerMw": 16942.2,
      "p99UpperMw": 58880.0
    },
    {
      "ts": "2025-10-28T17:00:00+09:00",
      "forecastMw": 37211.9,
      "p95LowerMw": 23476.5,
      "p95UpperMw": 50947.2,
      "p99LowerMw": 19159.7,
      "p99UpperMw": 55264.0
    },
    {
      "ts": "2025-10-28T18:00:00+09:00",
      "forecastMw": 36364.8,
      "p95LowerMw": 23424.5,
      "p95UpperMw": 49305.2,
      "p99LowerMw": 19357.5,
      "p99UpperMw": 53372.1
    },
    {
      "ts": "2025-10-28T19:00:00+09:00",
      "forecastMw": 34937.8,
      "p95LowerMw": 22680.5,
      "p95UpperMw": 47195.0,
      "p99LowerMw": 18828.3,
      "p99UpperMw": 51047.3
    },
    {
      "ts": "2025-10-28T20:00:00+09:00",
      "forecastMw": 33317.4,
      "p95LowerMw": 22021.5,
      "p95UpperMw": 44613.4,
      "p99LowerMw": 18471.3,
      "p99UpperMw": 48163.5
    },
    {
      "ts": "2025-10-28T21:00:00+09:00",
      "forecastMw": 31484.1,
      "p95LowerMw": 21066.1,
      "p95UpperMw": 41902.0,
      "p99LowerMw": 17791.9,
      "p99UpperMw": 45176.2
    },
    {
      "ts": "2025-10-28T22:00:00+09:00",
      "forecastMw": 29896.7,
      "p95LowerMw": 20412.8,
      "p95UpperMw": 39380.5,
      "p99LowerMw": 17432.1,
      "p99UpperMw": 42361.2
    },
    {
      "ts": "2025-10-28T23:00:00+09:00",
      "forecastMw": 28144.8,
      "p95LowerMw": 19770.6,
      "p95UpperMw": 36519.0,
      "p99LowerMw": 17138.7,
      "p99UpperMw": 39151.0
    }
  ]
}