{
  "date": "2026-01-01",
  "timezone": "Asia/Tokyo",
  "availability": "ok",
  "model": {
    "name": "baseline_dow_hour_mean",
    "version": "mvp-1",
    "nWeeks": 12
  },
  "peak": {
    "forecastMw": 34000.0,
    "at": "2026-01-01T19:00:00+09:00",
    "interval": {
      "p95Lower": 25355.0,
      "p95Upper": 42645.0
    }
  },
  "series": [
    {
      "ts": "2026-01-01T00:00:00+09:00",
      "forecastMw": 27112.9,
      "p95LowerMw": 23347.4,
      "p95UpperMw": 30878.3,
      "p99LowerMw": 22164.0,
      "p99UpperMw": 32061.7
    },
    {
      "ts": "2026-01-01T01:00:00+09:00",
      "forecastMw": 26015.7,
      "p95LowerMw": 22230.3,
      "p95UpperMw": 29801.2,
      "p99LowerMw": 21040.6,
      "p99UpperMw": 30990.9
    },
    {
      "ts": "2026-01-01T02:00:00+09:00",
      "forecastMw": 25585.7,
      "p95LowerMw": 21802.3,
      "p95UpperMw": 29369.1,
      "p99LowerMw": 20613.3,
      "p99UpperMw": 30558.2
    },
    {
      "ts": "2026-01-01T03:00:00+09:00",
      "forecastMw": 25437.1,
      "p95LowerMw": 21569.5,
      "p95UpperMw": 29304.8,
      "p99LowerMw": 20353.9,
      "p99UpperMw": 30520.3
    },
    {
      "ts": "2026-01-01T04:00:00+09:00",
      "forecastMw": 25497.1,
      "p95LowerMw": 21385.6,
      "p95UpperMw": 29608.7,
      "p99LowerMw": 20093.4,
      "p99UpperMw": 30900.9
    },
    {
      "ts": "2026-01-01T05:00:00+09:00",
      "forecastMw": 26170.0,
      "p95LowerMw": 21328.3,
      "p95UpperMw": 31011.7,
      "p99LowerMw": 19806.7,
      "p99UpperMw": 32533.3
    },
    {
      "ts": "2026-01-01T06:00:00+09:00",
      "forecastMw": 27895.7,
      "p95LowerMw": 21551.8,
      "p95UpperMw": 34239.6,
      "p99LowerMw": 19558.0,
      "p99UpperMw": 36233.4
    },
    {
      "ts": "2026-01-01T07:00:00+09:00",
      "forecastMw": 30071.4,
      "p95LowerMw": 22286.7,
      "p95UpperMw": 37856.2,
      "p99LowerMw": 19840.0,
      "p99UpperMw": 40302.8
    },
    {
      "ts": "2026-01-01T08:00:00+09:00",
      "forecastMw": 31408.6,
      "p95LowerMw": 22364.2,
      "p95UpperMw": 40452.9,
      "p99LowerMw": 19521.7,
      "p99UpperMw": 43295.4
    },
    {
      "ts": "2026-01-01T09:00:00+09:00",
      "forecastMw": 30872.9,
      "p95LowerMw": 21031.3,
      "p95UpperMw": 40714.5,
      "p99LowerMw": 17938.2,
      "p99UpperMw": 43807.5
    },
    {
      "ts": "2026-01-01T10:00:00+09:00",
      "forecastMw": 29728.6,
      "p95LowerMw": 20014.0,
      "p95UpperMw": 39443.1,
      "p99LowerMw": 16960.9,
      "p99UpperMw": 42496.2
    },
    {
      "ts": "2026-01-01T11:00:00+09:00",
      "forecastMw": 28768.6,
      "p95LowerMw": 19360.0,
      "p95UpperMw": 38177.1,
      "p99LowerMw": 16403.0,
      "p99UpperMw": 41134.1
    },
    {
      "ts": "2026-01-01T12:00:00+09:00",
      "forecastMw": 27970.0,
      "p95LowerMw": 19178.9,
      "p95UpperMw": 36761.1,
      "p99LowerMw": 16416.0,
      "p99UpperMw": 39524.0
    },
    {
      "ts": "2026-01-01T13:00:00+09:00",
      "forecastMw": 27554.3,
      "p95LowerMw": 18463.9,
      "p95UpperMw": 36644.7,
      "p99LowerMw": 15606.9,
      "p99UpperMw": 39501.7
    },
    {
      "ts": "2026-01-01T14:00:00+09:00",
      "forecastMw": 27580.0,
      "p95LowerMw": 18700.5,
      "p95UpperMw": 36459.5,
      "p99LowerMw": 15909.8,
      "p99UpperMw": 39250.2
    },
    {
      "ts": "2026-01-01T15:00:00+09:00",
      "forecastMw": 28475.7,
      "p95LowerMw": 19734.1,
      "p95UpperMw": 37217.3,
      "p99LowerMw": 16986.8,
      "p99UpperMw": 39964.7
    },
    {
      "ts": "2026-01-01T16:00:00+09:00",
      "forecastMw": 30381.4,
      "p95LowerMw": 21463.5,
      "p95UpperMw": 39299.3,
      "p99LowerMw": 18660.8,
      "p99UpperMw": 42102.1
    },
    {
      "ts": "2026-01-01T17:00:00+09:00",
      "forecastMw": 33121.4,
      "p95LowerMw": 24097.5,
      "p95UpperMw": 42145.4,
      "p99LowerMw": 21261.4,
      "p99UpperMw": 44981.5
    },
    {
      "ts": "2026-01-01T18:00:00+09:00",
      "forecastMw": 33974.3,
      "p95LowerMw": 24906.0,
      "p95UpperMw": 43042.5,
      "p99LowerMw": 22056.0,
      "p99UpperMw": 45892.6
    },
    {
      "ts": "2026-01-01T19:00:00+09:00",
      "forecastMw": 34000.0,
      "p95LowerMw": 25355.0,
      "p95UpperMw": 42645.0,
      "p99LowerMw": 22638.0,
      "p99UpperMw": 45362.0
    },
    {
      "ts": "2026-01-01T20:00:00+09:00",
      "forecastMw": 33741.4,
      "p95LowerMw": 25698.1,
      "p95UpperMw": 41784.7,
      "p99LowerMw": 23170.2,
      "p99UpperMw": 44312.6
    },
    {
      "ts": "2026-01-01T21:00:00+09:00",
      "forecastMw": 32852.9,
      "p95LowerMw": 25771.0,
      "p95UpperMw": 39934.7,
      "p99LowerMw": 23545.3,
      "p99UpperMw": 42160.4
    },
    {
      "ts": "2026-01-01T22:00:00+09:00",
      "forecastMw": 31154.3,
      "p95LowerMw": 25033.6,
      "p95UpperMw": 37275.0,
      "p99LowerMw": 23110.0,
      "p99UpperMw": 39198.6
    },
    {
      "ts": "2026-01-01T23:00:00+09:00",
      "forecastMw": 29535.7,
      "p95LowerMw": 24343.3,
      "p95UpperMw": 34728.1,
      "p99LowerMw": 22711.5,
      "p99UpperMw": 36360.0
    }
  ]
}